cmakelists_updater/__init__.py
cmakelists_updater/updater.py
cmakelists_updater-1.0.1.dist-info/LICENSE.txt
cmakelists_updater-1.0.1.dist-info/METADATA
cmakelists_updater-1.0.1.dist-info/WHEEL
cmakelists_updater-1.0.1.dist-info/entry_points.txt
cmakelists_updater-1.0.1.dist-info/top_level.txt
cmakelists_updater-1.0.1.dist-info/RECORD
