Metadata-Version: 2.1
Name: cmakelists-updater
Version: 1.0.1
Summary: A tool to auto-update CMakeLists.txt when source files change.
Home-page: https://github.com/obsqrbtz/cmakelists-autoupdater
Author: obsqrbtz
Author-email: dan@obsqrbtz.space
Keywords: cmake,automation,updater
Classifier: Programming Language :: Python :: 3
Classifier: License :: OSI Approved :: MIT License
Classifier: Operating System :: OS Independent
Requires-Python: >=3.6
License-File: LICENSE.txt
Requires-Dist: pyyaml==6.0.2
Requires-Dist: watchdog==6.0.0
